concurrent_plugin/__init__.py
concurrent_plugin/concurrent_backend.py
concurrent_plugin/concurrent_core.py
concurrent_plugin/concurrent_deployment.py
concurrent_plugin/login.py
concurrent_plugin/periodic_run.py
concurrent_plugin/utils.py
concurrent_plugin/infinfs/__init__.py
concurrent_plugin/infinfs/infin_download.py
concurrent_plugin/infinfs/infin_prefetch.py
concurrent_plugin/infinfs/infinfs.py
concurrent_plugin/infinfs/infinmount.py
concurrent_plugin/infinfs/mount_main.py
concurrent_plugin/infinfs/mount_service.py
concurrent_plugin-0.5.20.dist-info/METADATA
concurrent_plugin-0.5.20.dist-info/WHEEL
concurrent_plugin-0.5.20.dist-info/entry_points.txt
concurrent_plugin-0.5.20.dist-info/top_level.txt
concurrent_plugin-0.5.20.dist-info/RECORD
