Metadata-Version: 2.1
Name: concurrent-plugin
Version: 0.5.20
Summary: Plugin for Concurrent for MLFlow
Requires-Dist: mlflow >=1.21.0
Requires-Dist: jsons
Requires-Dist: kubernetes
Requires-Dist: dpath
Requires-Dist: traceback-with-variables
